nfinance/__init__.py
nfinance/financials.py
nfinance/rsi.py
nfinance/setup.py
nfinance/stock_data.py
nfinance/stock_listing.py
nfinance-0.4.22.dist-info/licenses/LICENSE
tests/__init__.py
tests/stock_data.py
tests/test_stock_data.py
nfinance-0.4.22.dist-info/METADATA
nfinance-0.4.22.dist-info/WHEEL
nfinance-0.4.22.dist-info/top_level.txt
nfinance-0.4.22.dist-info/RECORD
