Metadata-Version: 2.4
Name: nfinance
Version: 0.4.22
Summary: A simple finance data fetching library for Naver Finance data.
Home-page: https://github.com/lega001/nfinance
Author: lega001
Author-email: lega01077970523@gmail.com
Classifier: Development Status :: 3 - Alpha
Classifier: Intended Audience :: Developers
Classifier: License :: OSI Approved :: MIT License
Classifier: Programming Language :: Python :: 3
Classifier: Programming Language :: Python :: 3.7
Classifier: Programming Language :: Python :: 3.8
Requires-Python: >=3.6
License-File: LICENSE
Requires-Dist: pandas
Requires-Dist: requests
Requires-Dist: tqdm
Requires-Dist: ta
Dynamic: author
Dynamic: author-email
Dynamic: classifier
Dynamic: description
Dynamic: description-content-type
Dynamic: home-page
Dynamic: license-file
Dynamic: requires-dist
Dynamic: requires-python
Dynamic: summary
